Workbook

Sheet Parameters
A1: Parameter | B1: Value | F1: 2023 | G1: 2024 | H1: 2025 | I1: 2026 | J1: 2027 | K1: 2028
A2: Premium subscription per month | B2: 3.99 | E2: Projected number of users (exponential) | F2: 15000 | G2: =5.45*F2 -> 81750 | H2: =3.145*G2 -> 257103.75 | I2: =2.15*H2 -> 552773.06 | J2: =1.75*I2 -> 967352.86 | K2: =1.75*J2 -> 1692867.5
A3: Number of Muslims who have access to internet in the world (16-35 age) | B3: =1800000000*0.5/3 -> 300000000 | E3: add_rev per year | F3: =$B9*F2*$B10*30*12/1000 -> 16200 | G3: =$B9*G2*$B10*30*12/1000 -> 88290 | H3: =$B9*H2*$B10*30*12/1000 -> 277672.05 | I3: =$B9*I2*$B10*30*12/1000 -> 596994.91 | J3: =$B9*J2*$B10*30*12/1000 -> 1044741.1 | K3: =$B9*K2*$B10*30*12/1000 -> 1828296.9
A4: Number of Christians who have access to internet in the world (16-35 age) | B4: =2380000000*0.9/3 -> 714000000 | E4: subscription_rev per year | F4: =F2*$B$5*12*$B$2 -> 28728 | G4: =G2*$B$5*12*$B$2 -> 156567.6 | H4: =H2*$B$5*12*$B$2 -> 492405.1 | I4: =I2*$B$5*12*$B$2 -> 1058671 | J4: =J2*$B$5*12*$B$2 -> 1852674.2 | K4: =K2*$B$5*12*$B$2 -> 3242179.8
A5: premium sub percentage from total user base | B5: 0.04 | E5: donat_rev per year | F5: =(F3+F4)*$B27/(100%-$B27) -> 2364.6316 | G5: =(G3+G4)*$B27/(100%-$B27) -> 12887.242 | H5: =(H3+H4)*$B27/(100%-$B27) -> 40530.376 | I5: =(I3+I4)*$B27/(100%-$B27) -> 87140.309 | J5: =(J3+J4)*$B27/(100%-$B27) -> 152495.54 | K5: =(K3+K4)*$B27/(100%-$B27) -> 266867.2
A6: revenue from Premium subs per month if we cover all market | B6: =B2*(B3+B4)*B5 -> 161834400
A7: Google/Apple/Samsung/Amazon/MS Store commision | B7: 0.3 | E7: total revenue per year | F7: =SUM(F3:F5) -> 47292.632 | G7: =SUM(G3:G5) -> 257744.84 | H7: =SUM(H3:H5) -> 810607.53 | I7: =SUM(I3:I5) -> 1742806.2 | J7: =SUM(J3:J5) -> 3049910.8 | K7: =SUM(K3:K5) -> 5337343.9
A8: revenue from subs after commisions per month | B8: =B6*(1-B7) -> 113284080 | E8: total rev after commisions (30%) per year | F8: =F7*(1-$B$7) -> 33104.842 | G8: =G7*(1-$B$7) -> 180421.39 | H8: =H7*(1-$B$7) -> 567425.27 | I8: =I7*(1-$B$7) -> 1219964.3 | J8: =J7*(1-$B$7) -> 2134937.6 | K8: =K7*(1-$B$7) -> 3736140.8
A9: average number of add interactions a day for a active user | B9: 2
A10: avg eCPM (cost for 1000 interactions) | B10: 1.5 | E10: Eqip expense per year | F10: =B33 -> 14000 | G10: =F10*$B34-F10 -> 2100 | H10: =G10*$B34 -> 2415 | I10: =H10*$B34 -> 2777.25 | J10: =I10*$B34 -> 3193.8375 | K10: =J10*$B34 -> 3672.9131
A11: the salary of the Founder per month | B11: 3000 | E11: salary expenses per year | F11: =sum(B11:B20)*12 -> 184800 | G11: =1.1*F11+B23*12 -> 263280 | H11: =1.1*G11+C23*12*2 -> 289608 | I11: =1.1*H11+D23*12*3 -> 318568.8 | J11: =1.1*I11+E23*12*4 -> 350425.68 | K11: =1.1*J11+F23*12*4 -> 385468.25 | M11: Comments
A12: the salary of the Chief Technology Officer (CTO) per month | B12: 2000 | E12: cloud services expense per year | F12: =$B$22*F2 -> 1050 | G12: =$B$22*G2 -> 5722.5 | H12: =$B$22*H2 -> 17997.263 | I12: =$B$22*I2 -> 38694.114 | J12: =$B$22*J2 -> 67714.7 | K12: =$B$22*K2 -> 118500.73 | M12: #1 | N12: We rented a new office in 2026 for 30K$/year
A13: the salary of the UX/UI Designer per month | B13: 1200 | E13: rent expense per year | F13: =B21*12 -> 24000 | G13: =F13*1.05 -> 25200 | H13: =G13*1.05 -> 26460 | I13: =H13*1.05+30000 -> 57783 | J13: =I13*1.05 -> 60672.15 | K13: =J13*1.05 -> 63705.757 | M13: #2 | N13: Office rent rises 5% each year
A14: the salaries of 2 Mobile Software Developers per month | B14: 2000 | E14: Other expenses per year | F14: 1000 | G14: =1.2*F14 -> 1200 | H14: =1.2*G14 -> 1440 | I14: =1.2*H14 -> 1728 | J14: =1.2*I14 -> 2073.6 | K14: =1.2*J14 -> 2488.32 | M14: #3 | N14: We hire 5 more employees each year
A15: the salaries of 3 Religious Scholars/Researchers for content creation per month | B15: 750 | E15: Marketing expenses per year | F15: 50000 | G15: 50000 | H15: =0.1*H8 -> 56742.527 | I15: =0.1*I8 -> 121996.43 | J15: =0.1*J8 -> 213493.76 | K15: =0.1*K8 -> 373614.08 | M15: #4 | N15: Cloud services expense rises wih the user base growth
A16: the salaries of PR Manager per month | B16: 2100 | E16: Software Expense per year | F16: =B25 -> 8000 | G16: =F16*1.1 -> 8800 | H16: =G16*1.1 -> 9680 | I16: =H16*1.1 -> 10648 | J16: =I16*1.1 -> 11712.8 | K16: =J16*1.1 -> 12884.08 | M16: #5 | N16: Donations make up about 5% of the total revenue
A17: the salaries of 2 Quality Assurance (QA) Engineers per month | B17: 1400 | E17: Interest Expense | F17: =B26*0.15 -> 22500 | G17: =F17+C26*0.15 -> 52500 | H17: =$G17 -> 52500 | I17: =$G17 -> 52500 | J17: =$G17 -> 52500 | K17: =$G17 -> 52500 | M17: #6 | N17: Agreement with investors to 20% income share after positive incomes
A18: the salary of the Product Manager per month | B18: 1200 | E18: total expense per year | F18: =sum(F11:F16) -> 268850 | G18: =sum(G11:G16) -> 354202.5 | H18: =sum(H11:H17) -> 454427.79 | I18: =sum(I11:I16) -> 549418.35 | J18: =sum(J11:J16) -> 706092.69 | K18: =sum(K11:K16) -> 956661.21
A19: the salary of the Marketing Director per month | B19: 1400
A20: the salary of the Customer Support Representative per month | B20: 350 | E20: net income per year | F20: =F8-F18 -> -235745.16 | G20: =G8-G18 -> -173781.11 | H20: =H8-H18 -> 112997.48 | I20: =I8-I18 -> 670545.98 | J20: =J8-J18 -> 1428844.9 | K20: =K8-K18 -> 2779479.6
A21: Rent in Astana per month | B21: 2000 | E21: income after KZ taxes (20%) per year | F21: =IF(F20<0, F20, F20*0.8 ) -> -235745.16 | G21: =IF(G20<0, G20, G20*0.8 ) -> -173781.11 | H21: =IF(H20<0, H20, H20*0.8 ) -> 90397.984 | I21: =IF(I20<0, I20, I20*0.8 ) -> 536436.79 | J21: =IF(J20<0, J20, J20*0.8 ) -> 1143075.9 | K21: =IF(K20<0, K20, K20*0.8 ) -> 2223583.6
A22: Cloud services per year per users | B22: 0.07 | E22: income after payed dividents(20%) | F22: =IF(F21<0, F21,F21*0.8 ) -> -235745.16 | G22: =IF(G21<0, G21,G21*0.8 ) -> -173781.11 | H22: =IF(H21<0, H21,H21*0.8 ) -> 72318.387 | I22: =IF(I21<0, I21,I21*0.8 ) -> 429149.43 | J22: =IF(J21<0, J21,J21*0.8 ) -> 914460.73 | K22: =IF(K21<0, K21,K21*0.8 ) -> 1778866.9
A23: plus 5 employees per year all earning this much per month | B23: 5000
A24: Total VC investments for 3 years | B24: 200000 | C24: 350000 | D24: 400000
A25: Adobe + Google Drive + Github etc. per year | B25: 8000
A26: Initial Bank loan 1-2 | B26: 150000 | C26: 200000 | D26: 300000 | E26: 0 | F26: 0 | G26: 0
A27: expected donation revenue contribution | B27: 0.05
A28: Rent increase rate | B28: 0.05
A29: Income tax | B29: 0.2
A30: Furniture | B30: 3000
A31: Technichal equipment | B31: 10000
A32: Other | B32: 1000
A33: total equip | B33: =SUM(B30:B32) -> 14000
A34: rate of growth of equip | B34: 1.15
A35: assets valued period(years) | B35: 5
A36: part of income distributet to investors | B36: 0.2
A37: part of available cash assets spend on Research&Dev | B37: 0.54
A38: part for short term investment | B38: 0.18
A39: deffered tax coef | B39: =1-(RAND()/4+0.6) -> 0.35434276

Sheet Balance Sheet
A1: Assets | C1: 2023 | D1: 2024 | E1: 2025 | F1: 2026 | G1: 2027 | H1: 2028
A2: Current Assets
B3: Cash and cash equivalents | C3: =(C26+C30)*(100%-Parameters!$B37-Parameters!$B38) -> 81845.356 | D3: =(D26+D30)*(100%-Parameters!$B37-Parameters!$B38) -> 181972.39 | E3: =(E26+E30)*(100%-Parameters!$B37-Parameters!$B38) -> 325016.62 | F3: =(F26+F30)*(100%-Parameters!$B37-Parameters!$B38) -> 424231.1 | G3: =(G26+G30)*(100%-Parameters!$B37-Parameters!$B38) -> 692839.9 | H3: =(H26+H30)*(100%-Parameters!$B37-Parameters!$B38) -> 1141305.8
B4: Accounts Receivable | C4: 0 | D4: 0 | E4: 0 | F4: 0 | G4: 0 | H4: 0
B5: Short-term investments | C5: =(C26+C30)*Parameters!$B38 -> 52614.872 | D5: =(D26+D30)*Parameters!$B38 -> 116982.25 | E5: =(E26+E30)*Parameters!$B38 -> 208939.25 | F5: =(F26+F30)*Parameters!$B38 -> 272719.99 | G5: =(G26+G30)*Parameters!$B38 -> 445397.08 | H5: =(H26+H30)*Parameters!$B38 -> 733696.58
A6: Total current assets | C6: =SUM(C3:C5) -> 134460.23 | D6: =SUM(D3:D5) -> 298954.64 | E6: =SUM(E3:E5) -> 533955.87 | F6: =SUM(F3:F5) -> 696951.09 | G6: =SUM(G3:G5) -> 1138237 | H6: =SUM(H3:H5) -> 1875002.4
A7: Non-Current Assets
B8: Property, plant, and equipment | C8: =Parameters!B33 -> 14000 | D8: =C8+Parameters!G10 -> 16100 | E8: =D8+Parameters!H10 -> 18515 | F8: =E8+Parameters!I10 -> 21292.25 | G8: =F8+Parameters!J10 -> 24486.088 | H8: =G8+Parameters!K10 -> 28159.001
B9: (Less accumulated depreciation) | C9: =(C8*0.2) -> 2800 | D9: =C9+D8*0.2 -> 6020 | E9: =D9+E8*0.2 -> 9723 | F9: =E9+F8*0.2 -> 13981.45 | G9: =F9+G8*0.2 -> 18878.667 | H9: =G9+H8*0.2 -> 24510.468
B10: Long-term investments | C10: =(C26+C30)*Parameters!$B37 -> 157844.61 | D10: =(D26+D30)*Parameters!$B37 -> 350946.75 | E10: =(E26+E30)*Parameters!$B37 -> 626817.76 | F10: =(F26+F30)*Parameters!$B37 -> 818159.98 | G10: =(G26+G30)*Parameters!$B37 -> 1336191.2 | H10: =(H26+H30)*Parameters!$B37 -> 2201089.7
A11: Total Non-Current Assets | C11: =SUM(C8:C10) -> 174644.61 | D11: =SUM(D8:D10) -> 373066.75 | E11: =SUM(E8:E10) -> 655055.76 | F11: =SUM(F8:F10) -> 853433.68 | G11: =SUM(G8:G10) -> 1379556 | H11: =SUM(H8:H10) -> 2253759.2
A12: Total Assets | C12: =C6+C11 -> 309104.84 | D12: =D6+D11 -> 672021.39 | E12: =E6+E11 -> 1189011.6 | F12: =F6+F11 -> 1550384.8 | G12: =G6+G11 -> 2517793 | H12: =H6+H11 -> 4128761.6
A14: Liabilities and Owner's Equity
A15: Current Liabilities
B16: Short-term loans | C16: =Parameters!F12+Parameters!F16 -> 9050 | D16: =Parameters!G12+Parameters!G16 -> 14522.5 | E16: =Parameters!H12+Parameters!H16 -> 27677.263 | F16: =Parameters!I12+Parameters!I16 -> 49342.114 | G16: =Parameters!J12+Parameters!J16 -> 79427.5 | H16: =Parameters!K12+Parameters!K16 -> 131384.81
B17: Income taxes payable | C17: ='Income statement'!C21*(1-Parameters!$B39) -> 0 | D17: ='Income statement'!D21*(1-Parameters!$B39) -> 0 | E17: ='Income statement'!E21*(1-Parameters!$B39) -> 13987.451 | F17: ='Income statement'!F21*(1-Parameters!$B39) -> 79123.782 | G17: ='Income statement'!G21*(1-Parameters!$B39) -> 176952.37 | H17: ='Income statement'!H21*(1-Parameters!$B39) -> 351620.18
B18: Accrued salaries and wages | C18: ='Income statement'!C13 -> 184800 | D18: ='Income statement'!D13 -> 263280 | E18: ='Income statement'!E13 -> 289608 | F18: ='Income statement'!F13 -> 318568.8 | G18: ='Income statement'!G13 -> 350425.68 | H18: ='Income statement'!H13 -> 385468.25
B19: Current portion of long-term debt | C19: =Parameters!F17 -> 22500 | D19: =Parameters!G17 -> 52500 | E19: =Parameters!H17 -> 52500 | F19: =Parameters!I17 -> 52500 | G19: =Parameters!J17 -> 52500 | H19: =Parameters!K17 -> 52500
A20: Total current liabilities | C20: =SUM(C16:C19) -> 216350 | D20: =SUM(D16:D19) -> 330302.5 | E20: =SUM(E16:E19) -> 383772.71 | F20: =SUM(F16:F19) -> 499534.7 | G20: =SUM(G16:G19) -> 659305.55 | H20: =SUM(H16:H19) -> 920973.23
A21: Non-current Liabilities
B22: Long-term debt | C22: =Parameters!B26 -> 150000 | D22: =Parameters!C26 -> 200000 | E22: =Parameters!D26 -> 300000 | F22: =Parameters!E26 -> 0 | G22: =Parameters!F26 -> 0 | H22: =Parameters!G26 -> 0
B23: Deferred income tax | C23: ='Income statement'!C21-C17 -> 0 | D23: ='Income statement'!D21-D17 -> 0 | E23: ='Income statement'!E21-E17 -> 7676.4447 | F23: ='Income statement'!F21-F17 -> 43423.875 | G23: ='Income statement'!G21-G17 -> 97113.121 | H23: ='Income statement'!H21-H17 -> 192972.46
B24: Other | C24: =C12-(C26+C30) -> 16800 | D24: =D12-(D26+D30) -> 22120 | E24: =E12-(E26+E30) -> 28238 | F24: =F12-(F26+F30) -> 35273.7 | G24: =G12-(G26+G30) -> 43364.755 | H24: =H12-(H26+H30) -> 52669.468
A25: Total long-term liabilities | C25: =SUM(C22:C23) -> 150000 | D25: =SUM(D22:D23) -> 200000 | E25: =SUM(E22:E23) -> 307676.44 | F25: =SUM(F22:F23) -> 43423.875 | G25: =SUM(G22:G23) -> 97113.121 | H25: =SUM(H22:H23) -> 192972.46
A26: Total liabilities | C26: =C20+C25 -> 366350 | D26: =D20+D25 -> 530302.5 | E26: =E20+E25 -> 691449.16 | F26: =F20+F25 -> 542958.57 | G26: =G20+G25 -> 756418.67 | H26: =H20+H25 -> 1113945.7
A27: Equity
B28: Shareholders' equity | C28: =Parameters!B24 -> 200000 | D28: =Parameters!C24 -> 350000 | E28: =Parameters!D24 -> 400000 | F28: =E28*1.45 -> 580000 | G28: =F28*1.45 -> 841000 | H28: =G28*1.45 -> 1219450
B29: Retained earnings | C29: ='Income statement'!C23 -> -274045.16 | D29: ='Income statement'!D23 -> -230401.11 | E29: ='Income statement'!E23 -> 69324.467 | F29: ='Income statement'!F23 -> 392152.5 | G29: ='Income statement'!G23 -> 877009.56 | H29: ='Income statement'!H23 -> 1742696.4
A30: Total equity | C30: =SUM(C28:C29) -> -74045.158 | D30: =SUM(D28:D29) -> 119598.89 | E30: =SUM(E28:E29) -> 469324.47 | F30: =SUM(F28:F29) -> 972152.5 | G30: =SUM(G28:G29) -> 1718009.6 | H30: =SUM(H28:H29) -> 2962146.4
A32: Total Liabilities and Owner's Equity | C32: =C26+C30+C24 -> 309104.84 | D32: =D26+D30+D24 -> 672021.39 | E32: =E26+E30+E24 -> 1189011.6 | F32: =F26+F30+F24 -> 1550384.8 | G32: =G26+G30+G24 -> 2517793 | H32: =H26+H30+H24 -> 4128761.6

Sheet Income statement
A1: Revenue | C1: 2023 | D1: 2024 | E1: 2025 | F1: 2026 | G1: 2027 | H1: 2028
B2: Subscription | C2: =Parameters!F4 -> 28728 | D2: =Parameters!G4 -> 156567.6 | E2: =Parameters!H4 -> 492405.1 | F2: =Parameters!I4 -> 1058671 | G2: =Parameters!J4 -> 1852674.2 | H2: =Parameters!K4 -> 3242179.8
B3: Advertisement | C3: =Parameters!F3 -> 16200 | D3: =Parameters!G3 -> 88290 | E3: =Parameters!H3 -> 277672.05 | F3: =Parameters!I3 -> 596994.91 | G3: =Parameters!J3 -> 1044741.1 | H3: =Parameters!K3 -> 1828296.9
B4: Donations | C4: =Parameters!F5 -> 2364.6316 | D4: =Parameters!G5 -> 12887.242 | E4: =Parameters!H5 -> 40530.376 | F4: =Parameters!I5 -> 87140.309 | G4: =Parameters!J5 -> 152495.54 | H4: =Parameters!K5 -> 266867.2
A5: Total Revenues | C5: =SUM(C2:C4) -> 47292.632 | D5: =SUM(D2:D4) -> 257744.84 | E5: =SUM(E2:E4) -> 810607.53 | F5: =SUM(F2:F4) -> 1742806.2 | G5: =SUM(G2:G4) -> 3049910.8 | H5: =SUM(H2:H4) -> 5337343.9
A7: Expenses | C7: 2023 | D7: 2024 | E7: 2025 | F7: 2026 | G7: 2027 | H7: 2028
B8: Depreciation | C8: =C11/Parameters!$B35 -> 2800 | D8: =C8+D11/Parameters!$B35 -> 3220 | E8: =D8+E11/Parameters!$B35 -> 3703 | F8: =E8+F11/Parameters!$B35 -> 4258.45 | G8: =F8+G11/Parameters!$B35 -> 4897.2175 | H8: =G8+H11/Parameters!$B35-C11/Parameters!$B35 -> 2831.8001
B9: Interest expense | C9: =Parameters!F17 -> 22500 | D9: =Parameters!G17 -> 52500 | E9: =Parameters!H17 -> 52500 | F9: =Parameters!I17 -> 52500 | G9: =Parameters!J17 -> 52500 | H9: =Parameters!K17 -> 52500
B10: Rent | C10: =Parameters!F13 -> 24000 | D10: =Parameters!G13 -> 25200 | E10: =Parameters!H13 -> 26460 | F10: =Parameters!I13 -> 57783 | G10: =Parameters!J13 -> 60672.15 | H10: =Parameters!K13 -> 63705.757
B11: Utilites | C11: =Parameters!B33 -> 14000 | D11: =Parameters!G10 -> 2100 | E11: =Parameters!H10 -> 2415 | F11: =Parameters!I10 -> 2777.25 | G11: =Parameters!J10 -> 3193.8375 | H11: =Parameters!K10 -> 3672.9131
B12: Advertisement | C12: =Parameters!F15 -> 50000 | D12: =Parameters!G15 -> 50000 | E12: =Parameters!H15 -> 56742.527 | F12: =Parameters!I15 -> 121996.43 | G12: =Parameters!J15 -> 213493.76 | H12: =Parameters!K15 -> 373614.08
B13: Salaries and wages | C13: =Parameters!F11 -> 184800 | D13: =Parameters!G11 -> 263280 | E13: =Parameters!H11 -> 289608 | F13: =Parameters!I11 -> 318568.8 | G13: =Parameters!J11 -> 350425.68 | H13: =Parameters!K11 -> 385468.25
B14: Software | C14: =Parameters!F16 -> 8000 | D14: =Parameters!G16 -> 8800 | E14: =Parameters!H16 -> 9680 | F14: =Parameters!I16 -> 10648 | G14: =Parameters!J16 -> 11712.8 | H14: =Parameters!K16 -> 12884.08
B15: Web hosting and domains | C15: =Parameters!F12 -> 1050 | D15: =Parameters!G12 -> 5722.5 | E15: =Parameters!H12 -> 17997.263 | F15: =Parameters!I12 -> 38694.114 | G15: =Parameters!J12 -> 67714.7 | H15: =Parameters!K12 -> 118500.73
B16: Platform Comission | C16: =C5*Parameters!$B7 -> 14187.789 | D16: =D5*Parameters!$B7 -> 77323.453 | E16: =E5*Parameters!$B7 -> 243182.26 | F16: =F5*Parameters!$B7 -> 522841.86 | G16: =G5*Parameters!$B7 -> 914973.25 | H16: =H5*Parameters!$B7 -> 1601203.2
B17: Research and Development
A18: Total Expenses | C18: =sum(C8:C16) -> 321337.79 | D18: =sum(D8:D16) -> 488145.95 | E18: =sum(E8:E16) -> 702288.05 | F18: =sum(F8:F16) -> 1130067.9 | G18: =sum(G8:G16) -> 1679583.4 | H18: =sum(H8:H16) -> 2614380.8
B20: Net Income Before Taxes | C20: =C5-C18 -> -274045.16 | D20: =D5-D18 -> -230401.11 | E20: =E5-E18 -> 108319.48 | F20: =F5-F18 -> 612738.28 | G20: =G5-G18 -> 1370327.4 | H20: =H5-H18 -> 2722963.2
B21: Income tax expense | C21: =IF(C20<0, 0, C20*Parameters!$B29) -> 0 | D21: =IF(D20<0, 0, D20*Parameters!$B29) -> 0 | E21: =IF(E20<0, 0, E20*Parameters!$B29) -> 21663.896 | F21: =IF(F20<0, 0, F20*Parameters!$B29) -> 122547.66 | G21: =IF(G20<0, 0, G20*Parameters!$B29) -> 274065.49 | H21: =IF(H20<0, 0, H20*Parameters!$B29) -> 544592.63
B22: Investors dividents | C22: =if(C20<0, 0, C20*(100%-Parameters!$B29)*Parameters!$B36) -> 0 | D22: =if(D20<0, 0, D20*(100%-Parameters!$B29)*Parameters!$B36) -> 0 | E22: =if(E20<0, 0, E20*(100%-Parameters!$B29)*Parameters!$B36) -> 17331.117 | F22: =if(F20<0, 0, F20*(100%-Parameters!$B29)*Parameters!$B36) -> 98038.125 | G22: =if(G20<0, 0, G20*(100%-Parameters!$B29)*Parameters!$B36) -> 219252.39 | H22: =if(H20<0, 0, H20*(100%-Parameters!$B29)*Parameters!$B36) -> 435674.11
A23: Net Income | C23: =C20-C21-C22 -> -274045.16 | D23: =D20-D21-D22 -> -230401.11 | E23: =E20-E21-E22 -> 69324.467 | F23: =F20-F21-F22 -> 392152.5 | G23: =G20-G21-G22 -> 877009.56 | H23: =H20-H21-H22 -> 1742696.4
